skillfarm/__init__.py
skillfarm/admin.py
skillfarm/app_settings.py
skillfarm/apps.py
skillfarm/auth_hooks.py
skillfarm/constants.py
skillfarm/decorators.py
skillfarm/errors.py
skillfarm/forms.py
skillfarm/hooks.py
skillfarm/providers.py
skillfarm/tasks.py
skillfarm/urls.py
skillfarm/views.py
skillfarm/api/__init__.py
skillfarm/api/schema.py
skillfarm/api/skillfarm.py
skillfarm/api/helpers/__init__.py
skillfarm/api/helpers/core.py
skillfarm/api/helpers/skilldetails.py
skillfarm/helpers/__init__.py
skillfarm/helpers/discord.py
skillfarm/helpers/lazy.py
skillfarm/locale/django.pot
skillfarm/locale/cs_CZ/LC_MESSAGES/django.mo
skillfarm/locale/cs_CZ/LC_MESSAGES/django.po
skillfarm/locale/de/LC_MESSAGES/django.mo
skillfarm/locale/de/LC_MESSAGES/django.po
skillfarm/locale/es/LC_MESSAGES/django.mo
skillfarm/locale/es/LC_MESSAGES/django.po
skillfarm/locale/fr_FR/LC_MESSAGES/django.mo
skillfarm/locale/fr_FR/LC_MESSAGES/django.po
skillfarm/locale/it_IT/LC_MESSAGES/django.mo
skillfarm/locale/it_IT/LC_MESSAGES/django.po
skillfarm/locale/ja/LC_MESSAGES/django.mo
skillfarm/locale/ja/LC_MESSAGES/django.po
skillfarm/locale/ko_KR/LC_MESSAGES/django.mo
skillfarm/locale/ko_KR/LC_MESSAGES/django.po
skillfarm/locale/nl_NL/LC_MESSAGES/django.mo
skillfarm/locale/nl_NL/LC_MESSAGES/django.po
skillfarm/locale/pl_PL/LC_MESSAGES/django.mo
skillfarm/locale/pl_PL/LC_MESSAGES/django.po
skillfarm/locale/ru/LC_MESSAGES/django.mo
skillfarm/locale/ru/LC_MESSAGES/django.po
skillfarm/locale/sk/LC_MESSAGES/django.mo
skillfarm/locale/sk/LC_MESSAGES/django.po
skillfarm/locale/uk/LC_MESSAGES/django.mo
skillfarm/locale/uk/LC_MESSAGES/django.po
skillfarm/locale/zh_Hans/LC_MESSAGES/django.mo
skillfarm/locale/zh_Hans/LC_MESSAGES/django.po
skillfarm/management/__init__.py
skillfarm/management/commands/__init__.py
skillfarm/management/commands/skillfarm_load_prices.py
skillfarm/managers/__init__.py
skillfarm/managers/characterskill.py
skillfarm/managers/skillfarmaudit.py
skillfarm/managers/skillqueue.py
aa_skillfarm-1.0.4.dist-info/METADATA
aa_skillfarm-1.0.4.dist-info/WHEEL
aa_skillfarm-1.0.4.dist-info/licenses/LICENSE
aa_skillfarm-1.0.4.dist-info/RECORD
