Metadata-Version: 2.4
Name: aa-skillfarm
Version: 1.0.4
Summary: A Skillfarm Tracker Module for Alliance Auth
Project-URL: Changelog, https://github.com/Geuthur/aa-skillfarm/blob/master/CHANGELOG.md
Project-URL: Homepage, https://github.com/Geuthur/aa-skillfarm
Project-URL: Source, https://github.com/Geuthur/aa-skillfarm
Project-URL: Tracker, https://github.com/Geuthur/aa-skillfarm/issues
Author-email: Geuthur <devgeuthur@gmail.com>
License:                     GNU GENERAL PUBLIC LICENSE
License-File: LICENSE
Classifier: Environment :: Web Environment
Classifier: Framework :: Django
Classifier: Framework :: Django :: 4.2
Classifier: Intended Audience :: Developers
Classifier: License :: OSI Approved :: GNU General Public License v3 (GPLv3)
Classifier: Operating System :: OS Independent
Classifier: Programming Language :: Python
Classifier: Programming Language :: Python :: 3 :: Only
Classifier: Programming Language :: Python :: 3.10
Classifier: Programming Language :: Python :: 3.11
Classifier: Programming Language :: Python :: 3.12
Classifier: Programming Language :: Python :: 3.13
Classifier: Programming Language :: Python :: 3.14
Classifier: Topic :: Internet :: WWW/HTTP
Classifier: Topic :: Internet :: WWW/HTTP :: Dynamic Content
Requires-Python: >=3.10
Requires-Dist: allianceauth<5,>=4.10
Requires-Dist: django-esi<9,>=8
Requires-Dist: django-eveuniverse>=1.6
Requires-Dist: django-ninja
Provides-Extra: tests-allianceauth-latest
Requires-Dist: aa-discordnotify; extra == 'tests-allianceauth-latest'
Requires-Dist: allianceauth-discordbot; extra == 'tests-allianceauth-latest'
Requires-Dist: coverage; extra == 'tests-allianceauth-latest'
Requires-Dist: discordproxy; extra == 'tests-allianceauth-latest'
Requires-Dist: factory-boy; extra == 'tests-allianceauth-latest'
